toolviper/__init__.py
toolviper/config/client.param.json
toolviper/config/cloudflare.param.json
toolviper/config/tools.param.json
toolviper/dask/__init__.py
toolviper/dask/client.py
toolviper/dask/menrva.py
toolviper/dask/plugins/__init__.py
toolviper/dask/plugins/scheduler.py
toolviper/dask/plugins/worker.py
toolviper/utils/__init__.py
toolviper/utils/console.py
toolviper/utils/display.py
toolviper/utils/logger.py
toolviper/utils/parameter.py
toolviper/utils/protego.py
toolviper/utils/tools.py
toolviper/utils/data/__init__.py
toolviper/utils/data/cloudflare.py
toolviper/utils/plugins/__init__.py
toolviper/utils/plugins/worker_logger.py
toolviper-0.0.16.dist-info/licenses/LICENSE
toolviper-0.0.16.dist-info/METADATA
toolviper-0.0.16.dist-info/WHEEL
toolviper-0.0.16.dist-info/top_level.txt
toolviper-0.0.16.dist-info/RECORD
